fqmv-0.0.1.dist-info/METADATA
fqmv-0.0.1.dist-info/WHEEL
fqmv/__init__.py
fqmv/fqmv.cpython-311-darwin.so
fqmv-0.0.1.dist-info/RECORD
